bloatier/__init__.py
bloatier-0.1.2.dist-info/METADATA
bloatier-0.1.2.dist-info/WHEEL
bloatier-0.1.2.dist-info/top_level.txt
bloatier-0.1.2.dist-info/RECORD
