Metadata-Version: 2.1
Name: bloatier
Version: 0.1.2
Summary: Basic String Bloater/Debloater Algorithm.
Home-page: https://github.com/JohnLesterDev/bloatier
Author: John Lester Dev :>
Author-email: johnlesterincbusiness@gmail.com
License: UNKNOWN
Keywords: algorithm,string manipulation,conversion
Platform: UNKNOWN
Classifier: Programming Language :: Python :: 3
Classifier: Operating System :: OS Independent
Requires-Python: >=3.8
